MANIFEST.in
README.md
VERSION
requirements.txt
setup.py
docs/source/conf.py
unimatrix.ext.octet.egg-info/PKG-INFO
unimatrix.ext.octet.egg-info/SOURCES.txt
unimatrix.ext.octet.egg-info/dependency_links.txt
unimatrix.ext.octet.egg-info/requires.txt
unimatrix.ext.octet.egg-info/top_level.txt
unimatrix/ext/octet/__init__.py
unimatrix/ext/octet/apps.py
unimatrix/ext/octet/const.py
unimatrix/ext/octet/package.json
unimatrix/ext/octet/settings.py
unimatrix/ext/octet/urls.py
unimatrix/ext/octet/abstract/__init__.py
unimatrix/ext/octet/abstract/blobdao.py
unimatrix/ext/octet/domain/__init__.py
unimatrix/ext/octet/domain/blobfactory.py
unimatrix/ext/octet/domain/tests/__init__.py
unimatrix/ext/octet/domain/tests/test_integration_blob_factory.py
unimatrix/ext/octet/infra/__init__.py
unimatrix/ext/octet/infra/repo/__init__.py
unimatrix/ext/octet/infra/repo/abstractblob.py
unimatrix/ext/octet/infra/repo/django.py
unimatrix/ext/octet/infra/repo/sqlalchemy.py
unimatrix/ext/octet/infra/repo/tests/__init__.py
unimatrix/ext/octet/infra/repo/tests/blobrepositorybase.py
unimatrix/ext/octet/infra/repo/tests/test_integration_blobrepository.py
unimatrix/ext/octet/infra/repo/tests/test_integration_blobrepository_sqlalchemy.py
unimatrix/ext/octet/lib/__init__.py
unimatrix/ext/octet/lib/asyncdescriptor.py
unimatrix/ext/octet/lib/blobencrypter.py
unimatrix/ext/octet/lib/descriptor.py
unimatrix/ext/octet/lib/backends/__init__.py
unimatrix/ext/octet/lib/backends/azure.py
unimatrix/ext/octet/lib/backends/base.py
unimatrix/ext/octet/lib/backends/gcs.py
unimatrix/ext/octet/lib/backends/local.py
unimatrix/ext/octet/lib/backends/tests/__init__.py
unimatrix/ext/octet/lib/backends/tests/test_azure.py
unimatrix/ext/octet/lib/backends/tests/test_gcs.py
unimatrix/ext/octet/lib/backends/tests/test_local.py
unimatrix/ext/octet/lib/tests/__init__.py
unimatrix/ext/octet/lib/tests/test_descriptor_json.py
unimatrix/ext/octet/lib/tests/test_integration_blobencrypter.py
unimatrix/ext/octet/management/commands/blob.py
unimatrix/ext/octet/migrations/0001_initial.py
unimatrix/ext/octet/migrations/0002_blobreference.py
unimatrix/ext/octet/migrations/0003_blobreference_labels.py
