Metadata-Version: 2.1
Name: unimatrix.ext.octet
Version: 0.5.2
Summary: Enter a description for this Unimatrix package
Home-page: https://gitlab.com/unimatrixone/libraries/python-unimatrix
Author: Cochise Ruhulessin
Author-email: cochise.ruhulessin@wizardsofindustry.com
License: UNKNOWN
Platform: UNKNOWN
Classifier: Development Status :: 4 - Beta
Classifier: Environment :: Console
Classifier: Environment :: Web Environment
Classifier: Framework :: Django
Classifier: Framework :: Django CMS
Classifier: Framework :: Flask
Classifier: Intended Audience :: Developers
Classifier: Intended Audience :: Financial and Insurance Industry
Classifier: Intended Audience :: Healthcare Industry
Classifier: License :: Other/Proprietary License
Classifier: Operating System :: POSIX
Classifier: Operating System :: POSIX :: Linux
Classifier: Programming Language :: Python :: 3.7
Classifier: Programming Language :: Python :: 3.8
Classifier: Programming Language :: Python :: 3.9
Classifier: Programming Language :: Python :: 3 :: Only
Classifier: Topic :: Internet
Provides-Extra: all
Provides-Extra: django
Provides-Extra: gcp
Provides-Extra: azure
Provides-Extra: sqlalchemy
